LICENSE.txt
MANIFEST.in
README.md
setup.cfg
setup.py
bin/kegbot
bin/setup-kegbot.py
deploy/kegbot-nginx.conf
deploy/kegbot-supervisor.conf
deploy/kegweb.wsgi
deploy/travis/local_settings.py
kegbot.egg-info/PKG-INFO
kegbot.egg-info/SOURCES.txt
kegbot.egg-info/dependency_links.txt
kegbot.egg-info/entry_points.txt
kegbot.egg-info/requires.txt
kegbot.egg-info/top_level.txt
pykeg/__init__.py
pykeg/celery.py
pykeg/settings.py
pykeg/backend/__init__.py
pykeg/backend/backends.py
pykeg/backend/backends_test.py
pykeg/backend/exceptions.py
pykeg/backend/signals.py
pykeg/backup/__init__.py
pykeg/backup/backup.py
pykeg/backup/backup_test.py
pykeg/backup/exceptions.py
pykeg/backup/mysql.py
pykeg/backup/postgres.py
pykeg/backup/unknown_engine.py
pykeg/contrib/__init__.py
pykeg/contrib/demomode/__init__.py
pykeg/contrib/demomode/middleware.py
pykeg/contrib/demomode/urls.py
pykeg/contrib/demomode/util.py
pykeg/contrib/demomode/views.py
pykeg/contrib/demomode/management/__init__.py
pykeg/contrib/demomode/management/commands/__init__.py
pykeg/contrib/demomode/management/commands/load_demo_data.py
pykeg/contrib/demomode/templates/contrib/demomode/demo_notice.html
pykeg/contrib/foursquare/__init__.py
pykeg/contrib/foursquare/forms.py
pykeg/contrib/foursquare/foursquare_test.py
pykeg/contrib/foursquare/plugin.py
pykeg/contrib/foursquare/tasks.py
pykeg/contrib/foursquare/views.py
pykeg/contrib/foursquare/templates/contrib/foursquare/foursquare_admin_settings.html
pykeg/contrib/foursquare/templates/contrib/foursquare/foursquare_user_settings.html
pykeg/contrib/twitter/__init__.py
pykeg/contrib/twitter/forms.py
pykeg/contrib/twitter/plugin.py
pykeg/contrib/twitter/plugin_test.py
pykeg/contrib/twitter/tasks.py
pykeg/contrib/twitter/views.py
pykeg/contrib/twitter/templates/contrib/twitter/admin_settings.html
pykeg/contrib/twitter/templates/contrib/twitter/twitter_user_settings.html
pykeg/contrib/untappd/__init__.py
pykeg/contrib/untappd/forms.py
pykeg/contrib/untappd/oauth_client.py
pykeg/contrib/untappd/plugin.py
pykeg/contrib/untappd/tasks.py
pykeg/contrib/untappd/untappd_test.py
pykeg/contrib/untappd/views.py
