Metadata-Version: 1.0
Name: kegbot
Version: 1.2.3
Summary: Kegbot Server package.
Home-page: https://kegbot.org/
Author: Bevbot LLC
Author-email: info@bevbot.com
License: UNKNOWN
Platform: UNKNOWN
